mesa_models/boltzmann_wealth_model/__init__.py
mesa_models/boltzmann_wealth_model/model.py
mesa_models/boltzmann_wealth_model/server.py
mesa_models/epstein_civil_violence/__init__.py
mesa_models/epstein_civil_violence/agent.py
mesa_models/epstein_civil_violence/model.py
mesa_models/epstein_civil_violence/portrayal.py
mesa_models/epstein_civil_violence/server.py
mesa_models/schelling/__init__.py
mesa_models/schelling/model.py
mesa_models/schelling/run.py
mesa_models/schelling/run_ascii.py
mesa_models/schelling/server.py
mesa_models/wolf_sheep/__init__.py
mesa_models/wolf_sheep/agents.py
mesa_models/wolf_sheep/model.py
mesa_models/wolf_sheep/random_walk.py
mesa_models/wolf_sheep/scheduler.py
mesa_models/wolf_sheep/server.py
mesa_models/wolf_sheep/test_random_walk.py
mesa_models-0.1.0.dist-info/LICENSE
mesa_models-0.1.0.dist-info/METADATA
mesa_models-0.1.0.dist-info/WHEEL
mesa_models-0.1.0.dist-info/top_level.txt
mesa_models-0.1.0.dist-info/RECORD
