Metadata-Version: 2.1
Name: mesa-models
Version: 0.1.0
Summary: Importable Mesa models.
Author-email: Project Mesa Team <projectmesa@googlegroups.com>
License: Copyright 2022 Core Mesa Team and contributors
Requires-Python: >=3.8
License-File: LICENSE
